{
  "users": [
    {
      "username": "Henning",
      "password": "665465",
      "id": 6
    },
    {
      "username": "Henning",
      "password": "665465",
      "id": 7
    },
    {
      "username": "Henning",
      "password": "665465",
      "id": 8
    },
    {
      "username": "Henning",
      "password": "665465",
      "id": 9
    },
    {
      "username": "Henning",
      "password": "665465",
      "id": 10
    },
    {
      "username": "Henning",
      "password": "665465",
      "id": 11
    },
    {
      "username": "Henning",
      "password": "665465",
      "id": 12
    },
    {
      "username": "Henning",
      "password": "665465",
      "id": 13
    },
    {
      "username": "Henning",
      "password": "665465",
      "id": 14
    },
    {
      "username": "Henning",
      "password": "665465",
      "id": 15
    },
    {
      "username": "Henning",
      "password": "665465",
      "id": 16
    },
    {
      "username": "Henning",
      "password": "665465",
      "id": 17
    },
    {
      "username": "Henning",
      "password": "665465",
      "id": 18
    },
    {
      "username": "Henning",
      "password": "665465",
      "id": 19
    },
    {
      "username": "Henning",
      "password": "665465",
      "id": 20
    },
    {
      "username": "Henning",
      "password": "665465",
      "id": 21
    },
    {
      "username": "Henning",
      "password": "665465",
      "id": 22
    },
    {
      "username": "Henning",
      "password": "665465",
      "id": 23
    },
    {
      "username": "Henning",
      "password": "665465",
      "id": 24
    },
    {
      "username": "Henning",
      "password": "665465",
      "id": 25
    },
    {
      "username": "Henning",
      "password": "665465",
      "id": 26
    },
    {
      "username": "Henning",
      "password": "665465",
      "id": 27
    },
    {
      "username": "Henning",
      "password": "665465",
      "id": 28
    }
  ]
}